{"fileDirections":{"Notes/Data Structures And algorithems/Recurrence relation.md":"ltr","Notes/IOS/Swift/function builders.md":"ltr","Notes/Data Structures And algorithems/Asymptotic notations.md":"ltr","Notes/CS-barIlan/LatexShortcuts.md":"ltr","Notes/CS-barIlan/שנה א/סמסטר ב/סיכומים/עוצמות.md":"rtl","Notes/CS-barIlan/שנה א/סמסטר ב/ליניארית/ליניארית2 תרגיל 6.md":"ltr","Notes/CS-barIlan/שנה א/סמסטר ב/מבנה נתונים/מבנה נתונים תרגיל 3.md":"rtl","Notes/Data Structures And algorithems/Divide and conquer.md":"ltr","Notes/CS-barIlan/שנה א/סמסטר ב/בדידה/בדידה 2 תרגיל 7.md":"rtl","Notes/CS-barIlan/שנה א/סמסטר ב/ליניארית/ליניארית 2 תרגיל 7.md":"rtl","Notes/CS-barIlan/שנה א/סמסטר ב/אינפי/אינפי 2 תרגיל 8.md":"rtl","Notes/CS-barIlan/שנה א/סמסטר ב/בדידה/בדידה 2 תרגיל 8.md":"rtl","Notes/CS-barIlan/שנה א/סמסטר ב/אינפי/אינפי 2 תרגיל 9.md":"rtl","Notes/CS-barIlan/שנה א/סמסטר ב/מבנה נתונים/מבנה נתונים תרגיל 4.md":"rtl","Notes/CS-barIlan/שנה א/סמסטר ב/ליניארית/ליניארית 2 תרגיל 8.md":"rtl","Notes/CS-barIlan/שנה א/סמסטר ב/אינפי/אינפי 2 תרגיל 10.md":"rtl","Notes/CS-barIlan/שנה א/סמסטר ב/ליניארית/ליניארית 2 תרגיל 9.md":"rtl","Notes/CS-barIlan/שנה א/סמסטר ב/מבנה נתונים/מבנה נתונים תרגיל 5.md":"rtl","Notes/Data Structures And algorithems/radix sort.md":"ltr","Notes/CS-barIlan/שנה א/סמסטר ב/בדידה/בדידה תרגיל 9.md":"rtl","Notes/CS-barIlan/שנה א/סמסטר ב/אינפי/אינפי 2 תרגיל 11.md":"rtl","Notes/CS-barIlan/שנה א/סמסטר ב/אינפי/אינפי 2 תרגיל 12.md":"rtl","Notes/CS-barIlan/שנה א/סמסטר ב/מבנה נתונים/מבנה נתונים תרגיל 6.md":"ltr","Notes/Data Structures And algorithems/מבנה נתונים ואלגוריתמיקה - טומי קליין - סיכום הספרים.md":"rtl","Notes/CS-barIlan/שנה א/סמסטר ב/מבנה נתונים/מבחנים/2021 מועד א.md":"rtl","Notes/CS-barIlan/שנה א/סמסטר ב/מבנה נתונים/מבחנים/מועד א 2020.md":"rtl","Notes/CS-barIlan/שנה א/סמסטר ב/מבנה נתונים/מבחנים/מועד ב 2020.md":"rtl","Notes/CS-barIlan/שנה א/סמסטר ב/מבנה נתונים/מבחנים/מועד א 2019.md":"rtl","Notes/CS-barIlan/שנה א/סמסטר ב/מבנה נתונים/מבחנים/2019 מועד ב.md":"rtl","Notes/CS-barIlan/שנה א/סמסטר ב/מבנה נתונים/מבחנים/שאלות בתכנון דינאמי.md":"rtl","Notes/CS-barIlan/שנה א/סמסטר ב/בדידה/סיכום למבחן בדידה 2.md":"rtl"},"defaultDirection":"ltr","rememberPerFile":true,"setNoteTitleDirection":true,"setYamlDirection":false}